pytoml11-0.0.5.dist-info/WHEEL
pytoml11-0.0.5.dist-info/RECORD
pytoml11-0.0.5.dist-info/METADATA
pytoml11-0.0.5.dist-info/licenses/LICENCE
pytoml11/_value.pyi
pytoml11/_value.cpython-311-x86_64-linux-gnu.so
pytoml11/__init__.py
