Metadata-Version: 2.1
Name: pytoml11
Version: 0.0.5
Summary: Bindings for toml11
Author-Email: Thijs Miedema <opensource@tmiedema.com>
Classifier: Development Status :: 4 - Beta
Classifier: License :: OSI Approved :: MIT License
Classifier: Programming Language :: Python :: 3 :: Only
Classifier: Programming Language :: Python :: 3.9
Classifier: Programming Language :: Python :: 3.10
Classifier: Programming Language :: Python :: 3.11
Classifier: Programming Language :: Python :: 3.12
Classifier: Programming Language :: Python :: 3.13
Requires-Python: >=3.9
Provides-Extra: dev
Provides-Extra: ci
Provides-Extra: test
Requires-Dist: pytest; extra == "dev"
Requires-Dist: ruff; extra == "dev"
Requires-Dist: syrupy; extra == "dev"
Requires-Dist: cibuildwheel; extra == "ci"
Requires-Dist: pytest; extra == "test"
Requires-Dist: syrupy; extra == "test"
